cleanliness/__init__.py
cleanliness/version.py
cleanliness-0.1.1.dist-info/LICENSE
cleanliness-0.1.1.dist-info/METADATA
cleanliness-0.1.1.dist-info/WHEEL
cleanliness-0.1.1.dist-info/top_level.txt
cleanliness-0.1.1.dist-info/RECORD
